gkd/__init__.py
gkd-0.1.dist-info/LICENSE
gkd-0.1.dist-info/METADATA
gkd-0.1.dist-info/WHEEL
gkd-0.1.dist-info/entry_points.txt
gkd-0.1.dist-info/top_level.txt
gkd-0.1.dist-info/RECORD
