Metadata-Version: 2.1
Name: gkd
Version: 0.1
Summary: Python tools for LaTex
Home-page: https://github.com/thautwarm/gkd
Author: thautwarm
Author-email: twshere@outlook.com
License: mit
Keywords: LaTex
Platform: any
Classifier: Programming Language :: Python :: 3.7
Classifier: Programming Language :: Python :: 3.8
Classifier: Programming Language :: Python :: Implementation :: CPython
Requires-Python: >=3.7.0
Requires-Dist: paperbnf (>=1.0)
